{
  "spawnPosition": {
    "x": -1475.2,
    "y": 0.7,
    "z": 4741.6,
    "rotation": 158.8
  },
  "maxMonstersTotal": 1000,
  "ambientSpawns": [
    {
      "monsterType": "scp939",
      "maxPerPlayer": 8,
      "maxDistance": 60
    },
    {
      "monsterType": "kobold",
      "maxPerPlayer": 6,
      "maxDistance": 60
    },
    {
      "monsterType": "goblin",
      "maxPerPlayer": 5,
      "maxDistance": 60
    },
    {
      "monsterType": "orc",
      "maxPerPlayer": 4,
      "maxDistance": 60
    },
    {
      "monsterType": "orc_female",
      "maxPerPlayer": 4,
      "maxDistance": 60
    }
  ]
}
